README.rst
setup.py
src/backported/__init__.py
src/backported/logging/__init__.py
src/backported/logging/handlers/__init__.py
src/backported/logging/handlers/handlers.py
src/javactl/__init__.py
src/javactl/exceptions.py
src/javactl/javactl.py
src/javactl.egg-info/PKG-INFO
src/javactl.egg-info/SOURCES.txt
src/javactl.egg-info/dependency_links.txt
src/javactl.egg-info/entry_points.txt
src/javactl.egg-info/requires.txt
src/javactl.egg-info/top_level.txt
src/javactl/executor/__init__.py
src/javactl/executor/executor.py
src/javactl/logger/__init__.py
src/javactl/logger/console_logger.py
src/javactl/logger/logger.py
src/javactl/logger/logger_wrapper.py
src/javactl/logger/system_logger.py
src/javactl/setting/__init__.py
src/javactl/setting/app_setting.py
src/javactl/setting/arg_parser.py
src/javactl/setting/java_setting.py
src/javactl/setting/log_setting.py
src/javactl/setting/os_setting.py
src/javactl/setting/setting.py
src/javactl/util/__init__.py
src/javactl/util/data_size.py
src/javactl/util/util.py