Metadata-Version: 1.0
Name: javactl
Version: 0.2.1
Summary: YAML-Configurable Java Application Wrapper
Home-page: https://github.com/mogproject/javactl
Author: mogproject
Author-email: mogproj@gmail.com
License: Apache 2.0 License
Platform: UNKNOWN
